crystal_toolkit/__init__.py
crystal_toolkit/_version.py
crystal_toolkit/defaults.json
crystal_toolkit/defaults.py
crystal_toolkit/mpid_cache.json
crystal_toolkit/settings.py
crystal_toolkit/apps/__init__.py
crystal_toolkit/apps/app_metadata.yaml
crystal_toolkit/apps/constants.py
crystal_toolkit/apps/help.yaml
crystal_toolkit/apps/main.py
crystal_toolkit/apps/assets/crystaltoolkit.css
crystal_toolkit/apps/assets/doi_cache.json
crystal_toolkit/apps/assets/favicon.ico
crystal_toolkit/apps/assets/favicon.png
crystal_toolkit/apps/assets/main.ecd1960277cfe37b135f.css
crystal_toolkit/apps/assets/task_ids_on_load.json
crystal_toolkit/apps/assets/fonts/fa-brands-400.eot
crystal_toolkit/apps/assets/fonts/fa-brands-400.svg
crystal_toolkit/apps/assets/fonts/fa-brands-400.ttf
crystal_toolkit/apps/assets/fonts/fa-brands-400.woff
crystal_toolkit/apps/assets/fonts/fa-brands-400.woff2
crystal_toolkit/apps/assets/fonts/fa-regular-400.eot
crystal_toolkit/apps/assets/fonts/fa-regular-400.svg
crystal_toolkit/apps/assets/fonts/fa-regular-400.ttf
crystal_toolkit/apps/assets/fonts/fa-regular-400.woff
crystal_toolkit/apps/assets/fonts/fa-regular-400.woff2
crystal_toolkit/apps/assets/fonts/fa-solid-900.eot
crystal_toolkit/apps/assets/fonts/fa-solid-900.svg
crystal_toolkit/apps/assets/fonts/fa-solid-900.ttf
crystal_toolkit/apps/assets/fonts/fa-solid-900.woff
crystal_toolkit/apps/assets/fonts/fa-solid-900.woff2
crystal_toolkit/apps/examples/BaFe2As2_fs.json.gz
crystal_toolkit/apps/examples/BaTiO3_ph_bs.json
crystal_toolkit/apps/examples/BaTiO3_ph_dos.json
crystal_toolkit/apps/examples/GaN_bs.json
crystal_toolkit/apps/examples/GaN_dos.json
crystal_toolkit/apps/examples/Si_bs.json
crystal_toolkit/apps/examples/Si_dos.json
crystal_toolkit/apps/examples/__init__.py
crystal_toolkit/apps/examples/bandstructure.py
crystal_toolkit/apps/examples/basic_hello_structure.py
crystal_toolkit/apps/examples/basic_hello_structure_interactive.py
crystal_toolkit/apps/examples/basic_hello_world.py
crystal_toolkit-2026.1.22.post0.dist-info/licenses/LICENSE
crystal_toolkit-2026.1.22.post0.dist-info/METADATA
crystal_toolkit-2026.1.22.post0.dist-info/WHEEL
crystal_toolkit-2026.1.22.post0.dist-info/top_level.txt
crystal_toolkit-2026.1.22.post0.dist-info/RECORD
