Metadata-Version: 2.4
Name: crystal_toolkit
Version: 2026.1.22.post0
Summary: Crystal Toolkit is a web app framework from the Materials Project allowing Python
Author-email: Matt Horton <mkhorton@lbl.gov>
License: Crystal Toolkit Copyright (c) 2017, The Regents of the University of
Project-URL: repo, https://github.com/materialsproject/crystaltoolkit
Project-URL: docs, https://docs.crystaltoolkit.org
Requires-Python: >=3.10
License-File: LICENSE
Requires-Dist: dash-mp-components>=0.5.0rc0
Requires-Dist: dash>=2.11.0
Requires-Dist: flask-caching
Requires-Dist: frozendict
Requires-Dist: mp-api
Requires-Dist: pydantic-settings
Requires-Dist: pymatgen>=2024.10.22
Requires-Dist: scikit-image
Requires-Dist: scikit-learn
Requires-Dist: shapely
Requires-Dist: webcolors
Requires-Dist: ipython
Requires-Dist: boltztrap2<25.11.1
Provides-Extra: server
Requires-Dist: dash-extensions; extra == "server"
Requires-Dist: gunicorn[gevent]; extra == "server"
Requires-Dist: habanero; extra == "server"
Requires-Dist: hiphive; extra == "server"
Requires-Dist: redis; extra == "server"
Provides-Extra: robocrys
Requires-Dist: robocrys; extra == "robocrys"
Provides-Extra: temdiff
Requires-Dist: py4DSTEM>=0.13.11; extra == "temdiff"
Provides-Extra: fermi
Requires-Dist: ifermi; extra == "fermi"
Requires-Dist: pyfftw; extra == "fermi"
Provides-Extra: phonon
Requires-Dist: phonopy; extra == "phonon"
Provides-Extra: vtk
Requires-Dist: dash-vtk; extra == "vtk"
Provides-Extra: localenv
Requires-Dist: dscribe; extra == "localenv"
Provides-Extra: figures
Requires-Dist: kaleido; extra == "figures"
Provides-Extra: dev
Requires-Dist: black; extra == "dev"
Requires-Dist: dash[testing]; extra == "dev"
Requires-Dist: dephell; extra == "dev"
Requires-Dist: jinja2; extra == "dev"
Requires-Dist: pre-commit; extra == "dev"
Requires-Dist: recommonmark; extra == "dev"
Requires-Dist: sphinx_rtd_theme; extra == "dev"
Provides-Extra: test
Requires-Dist: playwright; extra == "test"
Requires-Dist: pytest; extra == "test"
Requires-Dist: pytest-playwright; extra == "test"
Requires-Dist: pytest-cov; extra == "test"
Requires-Dist: selenium<4; extra == "test"
Requires-Dist: urllib3<2; extra == "test"
Provides-Extra: jupyterlab-deprecated
Requires-Dist: crystaltoolkit-extension; extra == "jupyterlab-deprecated"
Dynamic: license-file
